rdotherinstock/__init__.py
rdotherinstock/mainModel.py
rdotherinstock/metadata.py
rdotherinstock/operation.py
rdotherinstock/utility.py
rdotherinstock-1.1.7.dist-info/METADATA
rdotherinstock-1.1.7.dist-info/WHEEL
rdotherinstock-1.1.7.dist-info/top_level.txt
rdotherinstock-1.1.7.dist-info/RECORD
